inui/__init__.py
inui/__main__.py
inui/base.py
inui/colors.py
inui/conf.py
inui/convert.py
inui/elements.py
inui/hotreload.py
inui/langs.py
inui/prettify.py
inui/query.py
inui/svg.py
inui/toinui.py
inui/bases/__init__.py
inui/bases/attributes.py
inui/bases/base.py
inui/bases/data.py
inui/bases/utils.py
inui/bootstrap/__init__.py
inui/bootstrap/utils.py
inui/config/__init__.py
inui/config/replaces.py
inui/css/__init__.py
inui/css/size.py
inui/css/utils.py
inui/fondation/__init__.py
inui/tailwind/__init__.py
inui/tailwind/utils.py
inui-1.0.0.7.dist-info/LICENSE
inui-1.0.0.7.dist-info/METADATA
inui-1.0.0.7.dist-info/WHEEL
inui-1.0.0.7.dist-info/entry_points.txt
inui-1.0.0.7.dist-info/top_level.txt
inui-1.0.0.7.dist-info/RECORD
