Metadata-Version: 2.1
Name: inui
Version: 1.0.0.7
Summary: Powerful and Highly Customizable Python Library for UI
Home-page: https://github.com/MohammadrezaAmani/INUI/
Author: Mohammadreza Amani
Author-email: Mohammadreza Amani <more.amani@yahoo.com>
License: MIT License
Project-URL: Homepage, https://github.com/MohammadrezaAmani/
Keywords: ui,python,html,framework,frontend,css,bootstrap,tailwind
Classifier: License :: OSI Approved :: MIT License
Classifier: Programming Language :: Python
Classifier: Programming Language :: Python :: 3
Requires-Python: >=3.5
License-File: LICENSE
Provides-Extra: full
Requires-Dist: black; extra == "full"
Requires-Dist: bs4; extra == "full"
Requires-Dist: lxml; extra == "full"
Requires-Dist: watchdog; extra == "full"
Requires-Dist: websockets; extra == "full"
